face_biometric_recognition/__init__.py
face_biometric_recognition/api.py
face_biometric_recognition-0.0.1.dist-info/LICENSE
face_biometric_recognition-0.0.1.dist-info/METADATA
face_biometric_recognition-0.0.1.dist-info/WHEEL
face_biometric_recognition-0.0.1.dist-info/top_level.txt
face_biometric_recognition-0.0.1.dist-info/RECORD
