Metadata-Version: 2.1
Name: face-biometric-recognition
Version: 0.0.1
Summary: Recognize faces from Python
Home-page: https://gitlab.com/vokeanighoro/facial_recognition
Author: Ransom Voke Anighoro
Author-email: voke.anighoro@gmail.com
License: MIT license
Keywords: face_biometric_recognition
Platform: UNKNOWN
Classifier: Development Status :: 4 - Beta
Classifier: Intended Audience :: Developers
Classifier: License :: OSI Approved :: MIT License
Classifier: Natural Language :: English
Classifier: Programming Language :: Python :: 3
Classifier: Programming Language :: Python :: 3.5
Classifier: Programming Language :: Python :: 3.6
Classifier: Programming Language :: Python :: 3.7
Classifier: Programming Language :: Python :: 3.8
Requires-Dist: face-recognition-models (>=0.3.0)
Requires-Dist: Click (>=6.0)
Requires-Dist: dlib (<=19.21.0,>=19.7)
Requires-Dist: numpy
Requires-Dist: Pillow
